yaspin/__init__.py
yaspin/api.py
yaspin/constants.py
yaspin/core.py
yaspin/data/spinners.json
yaspin/py.typed
yaspin/spinners.py
yaspin-3.2.0.dist-info/LICENSE
yaspin-3.2.0.dist-info/METADATA
yaspin-3.2.0.dist-info/WHEEL
yaspin-3.2.0.dist-info/RECORD
