Metadata-Version: 2.3
Name: yaspin
Version: 3.2.0
Summary: Yet Another Terminal Spinner
License: MIT
Keywords: spinner,console,terminal,loader,indicator
Author: Pavlo Dmytrenko
Author-email: pavdmyt@aiven.io
Requires-Python: >=3.9,<4.0
Classifier: Development Status :: 5 - Production/Stable
Classifier: Environment :: Console
Classifier: Environment :: MacOS X
Classifier: Environment :: Other Environment
Classifier: Intended Audience :: Developers
Classifier: Intended Audience :: End Users/Desktop
Classifier: Intended Audience :: Other Audience
Classifier: Intended Audience :: System Administrators
Classifier: License :: OSI Approved :: MIT License
Classifier: Natural Language :: English
Classifier: Operating System :: MacOS :: MacOS X
Classifier: Operating System :: POSIX :: Linux
Classifier: Programming Language :: Python
Classifier: Programming Language :: Python :: 3
Classifier: Programming Language :: Python :: 3.9
Classifier: Programming Language :: Python :: 3.10
Classifier: Programming Language :: Python :: 3.11
Classifier: Programming Language :: Python :: 3.12
Classifier: Programming Language :: Python :: 3.13
Classifier: Programming Language :: Python :: 3 :: Only
Classifier: Programming Language :: Python :: 3.14
Classifier: Programming Language :: Python :: Implementation
Classifier: Programming Language :: Python :: Implementation :: CPython
Classifier: Programming Language :: Python :: Implementation :: PyPy
Classifier: Topic :: Software Development
Classifier: Topic :: Software Development :: Libraries :: Python Modules
Classifier: Topic :: Software Development :: User Interfaces
Classifier: Topic :: System :: Logging
Classifier: Topic :: System :: Monitoring
Classifier: Topic :: System :: Shells
Classifier: Topic :: Terminals
Classifier: Topic :: Utilities
Requires-Dist: termcolor (>=3.1,<4.0)
Project-URL: Bug Tracker, https://github.com/pavdmyt/yaspin/issues
Project-URL: Changelog, https://github.com/pavdmyt/yaspin/releases
Project-URL: Documentation, https://github.com/pavdmyt/yaspin/blob/master/README.md
Project-URL: Homepage, https://github.com/pavdmyt/yaspin
Project-URL: Repository, https://github.com/pavdmyt/yaspin
